wwpdb/utils/dp/CentreOfMass.py
wwpdb/utils/dp/DataFileAdapter.py
wwpdb/utils/dp/DensityWrapper.py
wwpdb/utils/dp/DepositorSyncUtil.py
wwpdb/utils/dp/PdbxChemShiftReport.py
wwpdb/utils/dp/PdbxMergeCategory.py
wwpdb/utils/dp/PdbxModelComplexity.py
wwpdb/utils/dp/PdbxSFMapCoefficients.py
wwpdb/utils/dp/PdbxStripCategory.py
wwpdb/utils/dp/RcsbDpUtility.py
wwpdb/utils/dp/RunRemote.py
wwpdb/utils/dp/ValidationWrapper.py
wwpdb/utils/dp/__init__.py
wwpdb/utils/dp/electron_density/__init__.py
wwpdb/utils/dp/electron_density/common_functions.py
wwpdb/utils/dp/electron_density/em_density_map.py
wwpdb/utils/dp/electron_density/x_ray_density_map.py
wwpdb/utils/dp/metal/__init__.py
wwpdb/utils/dp/metal/findgeo/__init__.py
wwpdb/utils/dp/metal/findgeo/parseFindGeo.py
wwpdb/utils/dp/metal/findgeo/processFindGeo.py
wwpdb/utils/dp/metal/findgeo/runFindGeo.py
wwpdb/utils/dp/metal/metal_ref/CCD_exception_list.csv
wwpdb/utils/dp/metal/metal_ref/coord_classes_mapping_abbr.csv
wwpdb/utils/dp/metal/metal_ref/coord_classes_mapping_abbr.xlsx
wwpdb/utils/dp/metal/metal_ref/metal_coordination_number.csv
wwpdb/utils/dp/metal/metal_ref/metal_oxidation_state.csv
wwpdb/utils/dp/metal/metal_util/__init__.py
wwpdb/utils/dp/metal/metal_util/readRef.py
wwpdb/utils/dp/metal/metal_util/run_command.py
wwpdb/utils/dp/metal/metalcoord/__init__.py
wwpdb/utils/dp/metal/metalcoord/parseMetalCoord.py
wwpdb/utils/dp/metal/metalcoord/processMetalCoordStats.py
wwpdb/utils/dp/metal/metalcoord/processMetalCoordUpdate.py
wwpdb/utils/dp/metal/metalcoord/runAcedrg.py
wwpdb/utils/dp/metal/metalcoord/runMetalCoord.py
wwpdb/utils/dp/metal/metalcoord/runServalcat.py
wwpdb_utils_dp-0.59.4.dist-info/METADATA
wwpdb_utils_dp-0.59.4.dist-info/WHEEL
wwpdb_utils_dp-0.59.4.dist-info/licenses/LICENSE
wwpdb_utils_dp-0.59.4.dist-info/RECORD
